amode.py
setup.py
amode.egg-info/PKG-INFO
amode.egg-info/SOURCES.txt
amode.egg-info/dependency_links.txt
amode.egg-info/top_level.txt