Metadata-Version: 1.0
Name: amode
Version: 1.0.0
Summary: qian tao shu zu
Home-page: https://www.baidu.com
Author: wuchq
Author-email: snailquan@126.com
License: UNKNOWN
Platform: UNKNOWN
